rtdi_ducktape/CDCTransforms.py
rtdi_ducktape/Dataflow.py
rtdi_ducktape/LoaderDeltaLake.py
rtdi_ducktape/Loaders.py
rtdi_ducktape/Metadata.py
rtdi_ducktape/RowTransformations.py
rtdi_ducktape/SQLUtils.py
rtdi_ducktape/__init__.py
rtdi_ducktape-0.8.6.dist-info/METADATA
rtdi_ducktape-0.8.6.dist-info/WHEEL
rtdi_ducktape-0.8.6.dist-info/licenses/LICENSE
rtdi_ducktape-0.8.6.dist-info/RECORD
