Metadata-Version: 2.4
Name: rtdi_ducktape
Version: 0.8.6
Summary: Using DuckDB and Python as high speed ETL tool
Project-URL: Homepage, https://github.com/rtdi/ducktape
Project-URL: Issues, https://github.com/rtdi/ducktape/issues
Author-email: Werner Dähn <werner.daehn@rtdi.io>
License-Expression: Apache-2.0
License-File: LICENSE
Classifier: Operating System :: OS Independent
Classifier: Programming Language :: Python :: 3
Requires-Python: >=3.9
Requires-Dist: deltalake
Requires-Dist: duckdb
Requires-Dist: pyarrow
